{"version":"3.7.1","examples":[{"id":"./spec/rack_mechanics_spec.rb[1:1]","description":"wishes user a good morning in the morning","full_description":"App wishes user a good morning in the morning","status":"passed","file_path":"./spec/rack_mechanics_spec.rb","line_number":5,"run_time":0.040937,"pending_message":null},{"id":"./spec/rack_mechanics_spec.rb[1:2]","description":"wishes user a good afternoon in the afternoon","full_description":"App wishes user a good afternoon in the afternoon","status":"passed","file_path":"./spec/rack_mechanics_spec.rb","line_number":13,"run_time":0.000453,"pending_message":null}],"summary":{"duration":0.042575,"example_count":2,"failure_count":0,"pending_count":0,"errors_outside_of_examples_count":0},"summary_line":"2 examples, 0 failures"}